rivr_jwt/__init__.py
rivr_jwt/middleware.py
rivr_jwt/py.typed
tests/__init__.py
tests/test_middleware.py
rivr_jwt-0.2.0.dist-info/LICENSE
rivr_jwt-0.2.0.dist-info/METADATA
rivr_jwt-0.2.0.dist-info/WHEEL
rivr_jwt-0.2.0.dist-info/top_level.txt
rivr_jwt-0.2.0.dist-info/RECORD
