Metadata-Version: 2.1
Name: rivr-jwt
Version: 0.2.0
Summary: Making authentication with JWT (JSON Web Token) and rivr simple.
Home-page: https://github.com/rivrproject/rivr-jwt
Author: Kyle Fuller
Author-email: kyle@fuller.li
License: BSD
Platform: UNKNOWN
Classifier: Programming Language :: Python :: 3
Classifier: Programming Language :: Python :: 3.6
Classifier: Programming Language :: Python :: 3.7
Classifier: Programming Language :: Python :: 3.8
Classifier: Programming Language :: Python :: 3.9
Classifier: License :: OSI Approved :: BSD License
Requires-Dist: rivr (>=0.9.0)
Requires-Dist: PyJWT
